fileslicer/__init__.py
fileslicer/__main__.py
fileslicer/_core.py
fileslicer/_version.py
fileslicer/py.typed
fileslicer-0.1.0.dist-info/METADATA
fileslicer-0.1.0.dist-info/WHEEL
fileslicer-0.1.0.dist-info/entry_points.txt
fileslicer-0.1.0.dist-info/licenses/LICENSE.txt
fileslicer-0.1.0.dist-info/RECORD
